topsis/__init__.py
topsis/topsis.py
Topsis_Garv_102203753-0.1.dist-info/LICENSE
Topsis_Garv_102203753-0.1.dist-info/METADATA
Topsis_Garv_102203753-0.1.dist-info/WHEEL
Topsis_Garv_102203753-0.1.dist-info/entry_points.txt
Topsis_Garv_102203753-0.1.dist-info/top_level.txt
Topsis_Garv_102203753-0.1.dist-info/RECORD
