Metadata-Version: 2.2
Name: Topsis-Garv-102203753
Version: 0.1
Summary: A Python package implementing TOPSIS method for MCDM
Home-page: https://github.com/garv/topsis-package
Author: Garv
Author-email: garvchawla7@gmail.com
Classifier: Programming Language :: Python :: 3
Classifier: License :: OSI Approved :: MIT License
Classifier: Operating System :: OS Independent
Requires-Python: >=3.6
License-File: LICENSE
Requires-Dist: pandas
Requires-Dist: numpy
Dynamic: author
Dynamic: author-email
Dynamic: classifier
Dynamic: description
Dynamic: description-content-type
Dynamic: home-page
Dynamic: requires-dist
Dynamic: requires-python
Dynamic: summary
